bongsang/__init__.py
bongsang/datasets/__init__.py
bongsang/datasets/house.csv
bongsang/lm/__init__.py
bongsang/lm/lm.py
bongsang-0.1.5.dist-info/LICENSE
bongsang-0.1.5.dist-info/METADATA
bongsang-0.1.5.dist-info/WHEEL
bongsang-0.1.5.dist-info/top_level.txt
bongsang-0.1.5.dist-info/RECORD
