Metadata-Version: 2.1
Name: bongsang
Version: 0.1.5
Summary: A collection of statistics and machine learning libraries under the bongsang package
Home-page: https://github.com/bongsang/bongsang
Author: Bongsang Kim
Author-email: happykbs@gmail.com
Classifier: Programming Language :: Python :: 3
Classifier: Intended Audience :: Developers
Classifier: Intended Audience :: Education
Classifier: Topic :: Scientific/Engineering :: Mathematics
Classifier: Topic :: Scientific/Engineering :: Visualization
Classifier: License :: OSI Approved :: MIT License
Classifier: Operating System :: OS Independent
Requires-Python: >=3.6
License-File: LICENSE
Requires-Dist: numpy >=1.18.0
Requires-Dist: pandas >=1.0.0
Requires-Dist: matplotlib >=3.0.0
Requires-Dist: scikit-learn >=0.22.0
Requires-Dist: scipy >=1.4.0
